README.md
setup.py
utzpy/__init__.py
utzpy/cmp.py
utzpy/common.py
utzpy/ehp.py
utzpy/flp.py
utzpy/nlv1.py
utzpy.egg-info/PKG-INFO
utzpy.egg-info/SOURCES.txt
utzpy.egg-info/dependency_links.txt
utzpy.egg-info/top_level.txt