Metadata-Version: 2.1
Name: utzpy
Version: 1.0
Summary: tziot basic library
Home-page: https://github.com/jdhxyy/utz-python
Author: jdh99
Author-email: jdh821@163.com
License: UNKNOWN
Platform: UNKNOWN
